{"cameraMode":{"drawMode":0,"name":"Shaded","section":"Shading Mode"},"sceneLighting":true,"audioPlay":false,"sceneViewState":{"m_AlwaysRefresh":false,"showFog":true,"showSkybox":true,"showFlares":true,"showImageEffects":true,"showParticleSystems":true,"showVisualEffectGraphs":true,"m_FxEnabled":true},"in2DMode":false,"pivot":{"x":-16.70755386352539,"y":-23.886280059814454,"z":-4.779040336608887},"rotation":{"x":0.2158309519290924,"y":-0.688750684261322,"z":0.22740283608436585,"w":0.6537022590637207},"size":38.92242431640625,"orthographic":false}